m2rr.py
m2rr-0.2.3.dist-info/LICENSE
m2rr-0.2.3.dist-info/METADATA
m2rr-0.2.3.dist-info/WHEEL
m2rr-0.2.3.dist-info/entry_points.txt
m2rr-0.2.3.dist-info/top_level.txt
m2rr-0.2.3.dist-info/RECORD
