Metadata-Version: 2.1
Name: m2rr
Version: 0.2.3
Summary: Convert Markdown to reStructuredText, m2rr.
Home-page: https://github.com/qhua948/m2rr
Author: Edward Huang
Author-email: e.huang@gns.cri.nz
License: MIT
Keywords: Markdown reStructuredText sphinx-extension
Platform: UNKNOWN
Classifier: Development Status :: 4 - Beta
Classifier: Framework :: Sphinx :: Extension
Classifier: Intended Audience :: Developers
Classifier: License :: OSI Approved :: MIT License
Classifier: Natural Language :: English
Classifier: Programming Language :: Python :: 2
Classifier: Programming Language :: Python :: 2.7
Classifier: Programming Language :: Python :: 3
Classifier: Programming Language :: Python :: 3.4
Classifier: Programming Language :: Python :: 3.5
Classifier: Programming Language :: Python :: 3.6
Classifier: Programming Language :: Python :: 3.7
Classifier: Programming Language :: Python :: 3.8
Classifier: Topic :: Text Processing
Requires-Dist: mistune
Requires-Dist: docutils
